mariamillet_de_toolkit/01-Package-creation.code-workspace
mariamillet_de_toolkit/__init__.py
mariamillet_de_toolkit/main.py
mariamillet_de_toolkit/vm.py
mariamillet_de_toolkit-0.1.0.dist-info/METADATA
mariamillet_de_toolkit-0.1.0.dist-info/WHEEL
mariamillet_de_toolkit-0.1.0.dist-info/entry_points.txt
mariamillet_de_toolkit-0.1.0.dist-info/RECORD
